[1,["c8tNuqg11Ba6gCf7kMdpju","9147DqhrhOu5CqEMk9G/84","2eKhCX25NFm4DZp2DFNbif","aev5FGrSVIJLlkHDB6HSog","20zjBdDwZCkIWkiZIDd3hY","4fs1H46cpMeL3X+GGSkuh0","160AePqJlJvYMtOw3wDTb5","52JxO0Cq1JhrhTuhyqEHoc","dahZ4WtWVBtJWHZS71Hoju","1fIBG6VOtOKbGZqB3z6ZsX"],["_textureSetter","value"],["cc.SpriteFrame",["cc.AnimationClip",["_name","_duration","speed","wrapMode","curveData"],-1,11]],[[1,0,1,2,3,4,5]],[[[{"name":"moving04","rect":[0,0,91,89],"offset":[0,0],"originalSize":[91,89],"capInsets":[0,0,0,0]}],[0],0,[0],[0],[0]],[[{"name":"moving01","rect":[0,0,88,91],"offset":[0,0],"originalSize":[88,91],"capInsets":[0,0,0,0]}],[0],0,[0],[0],[1]],[[{"name":"moving02","rect":[0,0,92,82],"offset":[0,0],"originalSize":[92,82],"capInsets":[0,0,0,0]}],[0],0,[0],[0],[2]],[[{"name":"moving03","rect":[0,0,88,86],"offset":[0,0],"originalSize":[88,86],"capInsets":[0,0,0,0]}],[0],0,[0],[0],[3]],[[[0,"fireAni",0.21666666666666667,0.5,2,[{},"comps",11,[{},"cc.Sprite",11,[{},"spriteFrame",12,[[[{"frame":0},"value",6,0],[{"frame":0.05},"value",6,1],[{"frame":0.1},"value",6,2],[{"frame":0.15},"value",6,3],[{"frame":0.2},"value",6,4]],11,11,11,11,11]]]]]],0,0,[0,0,0,0,0],[1,1,1,1,1],[4,5,6,7,8]],[[{"name":"moving05","rect":[0,0,94,84],"offset":[0,0],"originalSize":[94,84],"capInsets":[0,0,0,0]}],[0],0,[0],[0],[9]]]]